scikit_fem-12.0.0.dist-info/licenses/LICENSE
skfem/__about__.py
skfem/__init__.py
skfem/generic_utils.py
skfem/helpers.py
skfem/quadrature.py
skfem/refdom.py
skfem/supermeshing.py
skfem/utils.py
skfem/assembly/__init__.py
skfem/assembly/dofs.py
skfem/assembly/basis/__init__.py
skfem/assembly/basis/abstract_basis.py
skfem/assembly/basis/cell_basis.py
skfem/assembly/basis/composite_basis.py
skfem/assembly/basis/facet_basis.py
skfem/assembly/basis/interior_facet_basis.py
skfem/assembly/form/__init__.py
skfem/assembly/form/bilinear_form.py
skfem/assembly/form/coo_data.py
skfem/assembly/form/form.py
skfem/assembly/form/functional.py
skfem/assembly/form/linear_form.py
skfem/assembly/form/trilinear_form.py
skfem/autodiff/__init__.py
skfem/autodiff/helpers.py
skfem/element/__init__.py
skfem/element/discrete_field.py
skfem/element/element.py
skfem/element/element_composite.py
skfem/element/element_dg.py
skfem/element/element_global.py
skfem/element/element_h1.py
skfem/element/element_hcurl.py
skfem/element/element_hdiv.py
skfem/element/element_matrix.py
skfem/element/element_vector.py
skfem/element/element_wedge_1.py
skfem/element/element_hex/__init__.py
skfem/element/element_hex/element_hex0.py
skfem/element/element_hex/element_hex1.py
skfem/element/element_hex/element_hex2.py
skfem/element/element_hex/element_hex_c1.py
skfem/element/element_hex/element_hex_rt1.py
skfem/element/element_hex/element_hex_s2.py
skfem/element/element_hex/element_hex_skeleton0.py
skfem/element/element_line/__init__.py
skfem/element/element_line/element_line_hermite.py
skfem/element/element_line/element_line_mini.py
skfem/element/element_line/element_line_p0.py
skfem/element/element_line/element_line_p1.py
skfem/element/element_line/element_line_p2.py
skfem/element/element_line/element_line_pp.py
skfem/element/element_quad/__init__.py
skfem/element/element_quad/element_quad0.py
skfem/element/element_quad/element_quad1.py
skfem/element/element_quad/element_quad2.py
skfem/element/element_quad/element_quad2g.py
scikit_fem-12.0.0.dist-info/METADATA
scikit_fem-12.0.0.dist-info/WHEEL
scikit_fem-12.0.0.dist-info/top_level.txt
scikit_fem-12.0.0.dist-info/RECORD
