Metadata-Version: 2.4
Name: scikit-fem
Version: 12.0.0
Summary: Simple finite element assemblers
Home-page: https://github.com/kinnala/scikit-fem
Author: Tom Gustafsson
License: BSD-3-Clause
Project-URL: Code, https://github.com/kinnala/scikit-fem
Project-URL: Issues, https://github.com/kinnala/scikit-fem/issues
Classifier: Intended Audience :: Science/Research
Classifier: Operating System :: OS Independent
Classifier: License :: OSI Approved :: BSD License
Classifier: Programming Language :: Python
Classifier: Programming Language :: Python :: 3
Classifier: Programming Language :: Python :: 3.10
Classifier: Programming Language :: Python :: 3.11
Classifier: Programming Language :: Python :: 3.12
Classifier: Programming Language :: Python :: 3.13
Classifier: Programming Language :: Python :: 3.14
Classifier: Topic :: Scientific/Engineering
Classifier: Topic :: Utilities
Requires-Python: >=3.10
License-File: LICENSE
Requires-Dist: numpy
Requires-Dist: scipy
Provides-Extra: all
Requires-Dist: meshio>=4.0.4; extra == "all"
Requires-Dist: matplotlib; extra == "all"
Dynamic: license-file
